yinyang/__init__.py
yinyang/config/Config.py
yinyang/config/OpfuzzHelptext.py
yinyang/config/TypefuzzHelptext.py
yinyang/config/YinyangHelptext.py
yinyang/config/__init__.py
yinyang/config/fusion_functions.txt
yinyang/config/operator_mutations.txt
yinyang/config/option_setting.txt
yinyang/config/typefuzz_config.txt
yinyang/src/__init__.py
yinyang/src/base/ArgumentParser.py
yinyang/src/base/Driver.py
yinyang/src/base/Error.py
yinyang/src/base/Exitcodes.py
yinyang/src/base/Utils.py
yinyang/src/base/Version.py
yinyang/src/base/__init__.py
yinyang/src/core/Fuzzer.py
yinyang/src/core/FuzzerUtil.py
yinyang/src/core/Logger.py
yinyang/src/core/OptionGenerator.py
yinyang/src/core/Solver.py
yinyang/src/core/Statistic.py
yinyang/src/core/__init__.py
yinyang/src/mutators/Mutator.py
yinyang/src/mutators/TypeAwareOpMutation.py
yinyang/src/mutators/__init__.py
yinyang/src/mutators/GenTypeAwareMutation/GenTypeAwareMutation.py
yinyang/src/mutators/GenTypeAwareMutation/Operator.py
yinyang/src/mutators/GenTypeAwareMutation/Util.py
yinyang/src/mutators/GenTypeAwareMutation/__init__.py
yinyang/src/mutators/SemanticFusion/SemanticFusion.py
yinyang/src/mutators/SemanticFusion/Util.py
yinyang/src/mutators/SemanticFusion/VariableFusion.py
yinyang/src/mutators/SemanticFusion/__init__.py
yinyang/src/parsing/Ast.py
yinyang/src/parsing/AstVisitor.py
yinyang/src/parsing/Parse.py
yinyang/src/parsing/SMTLIBv2Lexer.py
yinyang/src/parsing/SMTLIBv2Listener.py
yinyang/src/parsing/SMTLIBv2Parser.py
yinyang/src/parsing/SMTLIBv2Visitor.py
yinyang/src/parsing/TimeoutDecorator.py
yinyang/src/parsing/Typechecker.py
yinyang/src/parsing/Types.py
yinyang/src/parsing/__init__.py
yinyang-0.3.0.data/scripts/opfuzz
yinyang-0.3.0.data/scripts/typefuzz
yinyang-0.3.0.data/scripts/yinyang
yinyang-0.3.0.dist-info/LICENSE.md
yinyang-0.3.0.dist-info/METADATA
yinyang-0.3.0.dist-info/WHEEL
yinyang-0.3.0.dist-info/top_level.txt
yinyang-0.3.0.dist-info/RECORD
