Metadata-Version: 2.1
Name: yinyang
Version: 0.3.0
Summary: A fuzzing framework for SMT solvers
Home-page: https://testsmt.github.io/
Author: Dominik Winterer, Chengyu Zhang, Jiwon Park, Zhendong Su
Author-email: dominik.winterer@inf.ethz.ch, dale.chengyu.zhang@gmail.com, jiwon.park@polytechnique.edu, ‎zhendong.su@inf.ethz.ch
License: UNKNOWN
Project-URL: Bug Tracker, https://github.com/testsmt/yinyang/issues
Project-URL: Documentation, https://yinyang.readthedocs.io/en/latest/
Project-URL: Source Code, https://github.com/testsmt/yinyang
Platform: UNKNOWN
Classifier: Programming Language :: Python :: 3
Classifier: License :: OSI Approved :: MIT License
Classifier: Operating System :: OS Independent
Requires-Python: >=3.6
License-File: LICENSE.md
Requires-Dist: antlr4-python3-runtime (==4.9.2)
